aanalyticsactauth/__init__.py
aanalyticsactauth/__version__.py
aanalyticsactauth/auth.py
aanalyticsactauth-0.0.2.dist-info/METADATA
aanalyticsactauth-0.0.2.dist-info/WHEEL
aanalyticsactauth-0.0.2.dist-info/top_level.txt
aanalyticsactauth-0.0.2.dist-info/RECORD
