Metadata-Version: 2.1
Name: aanalyticsactauth
Version: 0.0.2
Summary: auth file for aanlayticsact
Home-page: https://github.com/SunkyeongLee/aanalyticsactauth
Author: Sunkyeong Lee
Author-email: sunkyeong.lee@concentrix.com
Classifier: Programming Language :: Python :: 3
Classifier: License :: OSI Approved :: MIT License
Classifier: Operating System :: OS Independent
Requires-Python: >=3.6
